{
  "title": "Norwegian",
  "image": "/page-images/norwegian.jpg",
  "description": "Denne nettsiden kartlegger ressurser kulturskapere og iverksettere i Tromsø kan bruke for å gjennomføre sine prosjekter. Ressursene kan sorteres i forskjellige kategorier. Vi har valgt å ha kartet på engelsk, for at flere skal kunne koble seg på og bli en del av kulturlivet i byen.",
  "meta": "Denne nettsiden kartlegger ressurser kulturskapere og iverksettere i Tromsø kan bruke for å gjennomføre sine prosjekter.",
  "sections": []
}
